confluence_sync/__init__.py
confluence_sync/cli.py
confluence_sync/config.py
confluence_sync/confluence_client.py
confluence_sync/sync.py
confluence_sync-0.1.0.dist-info/WHEEL
confluence_sync-0.1.0.dist-info/entry_points.txt
confluence_sync-0.1.0.dist-info/METADATA
confluence_sync-0.1.0.dist-info/RECORD
