Metadata-Version: 2.3
Name: confluence-sync
Version: 0.1.0
Summary: Tool to sync Confluence pages with local markdown files using version control
Keywords: confluence,markdown,sync,documentation,atlassian
Author: shouhanzen
Author-email: shouhanzen <shouhanzen@gmail.com>
License: MIT
Classifier: Development Status :: 4 - Beta
Classifier: Intended Audience :: Developers
Classifier: Topic :: Documentation
Classifier: Topic :: Software Development :: Documentation
Classifier: License :: OSI Approved :: MIT License
Classifier: Programming Language :: Python :: 3
Classifier: Programming Language :: Python :: 3.9
Classifier: Programming Language :: Python :: 3.10
Classifier: Programming Language :: Python :: 3.11
Classifier: Programming Language :: Python :: 3.12
Classifier: Programming Language :: Python :: 3.13
Requires-Dist: atlassian-python-api>=3.41.0
Requires-Dist: click>=8.1.7
Requires-Dist: pydantic>=2.5.0
Requires-Dist: pyyaml>=6.0.1
Requires-Dist: rich>=13.7.0
Requires-Dist: markdownify>=0.11.6
Requires-Python: >=3.9
Project-URL: Homepage, https://github.com/shouhanzen/confluence-sync
Project-URL: Issues, https://github.com/shouhanzen/confluence-sync/issues
Project-URL: Repository, https://github.com/shouhanzen/confluence-sync
